phoenix/__init__.py
phoenix/config.py
phoenix/datetime_utils.py
phoenix/exceptions.py
phoenix/py.typed
phoenix/services.py
phoenix/settings.py
phoenix/version.py
phoenix/core/__init__.py
phoenix/core/embedding_dimension.py
phoenix/core/model.py
phoenix/core/model_schema.py
phoenix/core/model_schema_adapter.py
phoenix/db/README.md
phoenix/db/__init__.py
phoenix/db/alembic.ini
phoenix/db/bulk_inserter.py
phoenix/db/engines.py
phoenix/db/helpers.py
phoenix/db/migrate.py
phoenix/db/models.py
phoenix/db/insertion/__init__.py
phoenix/db/insertion/evaluation.py
phoenix/db/insertion/helpers.py
phoenix/db/insertion/span.py
phoenix/db/migrations/__init__.py
phoenix/db/migrations/env.py
phoenix/db/migrations/script.py.mako
phoenix/db/migrations/versions/cf03bd6bae1d_init.py
phoenix/inferences/__init__.py
phoenix/inferences/errors.py
phoenix/inferences/fixtures.py
phoenix/inferences/inferences.py
phoenix/inferences/schema.py
phoenix/inferences/validation.py
phoenix/metrics/README.md
phoenix/metrics/__init__.py
phoenix/metrics/binning.py
phoenix/metrics/metrics.py
phoenix/metrics/mixins.py
phoenix/metrics/retrieval_metrics.py
phoenix/metrics/timeseries.py
phoenix/metrics/wrappers.py
phoenix/pointcloud/__init__.py
phoenix/pointcloud/clustering.py
phoenix/pointcloud/pointcloud.py
phoenix/pointcloud/projectors.py
phoenix/pointcloud/umap_parameters.py
phoenix/server/__init__.py
phoenix/server/app.py
phoenix/server/grpc_server.py
phoenix/server/main.py
phoenix/server/prometheus.py
phoenix/server/telemetry.py
phoenix/server/thread_server.py
phoenix/server/api/__init__.py
phoenix/server/api/context.py
phoenix/server/api/helpers.py
phoenix/server/api/interceptor.py
phoenix/server/api/schema.py
phoenix/server/api/dataloaders/__init__.py
phoenix/server/api/dataloaders/document_evaluation_summaries.py
phoenix/server/api/dataloaders/document_evaluations.py
phoenix/server/api/dataloaders/document_retrieval_metrics.py
phoenix/server/api/dataloaders/evaluation_summaries.py
astra_logs-4.2.8.dist-info/METADATA
astra_logs-4.2.8.dist-info/WHEEL
astra_logs-4.2.8.dist-info/licenses/IP_NOTICE
astra_logs-4.2.8.dist-info/licenses/LICENSE
astra_logs-4.2.8.dist-info/RECORD
