Metadata-Version: 2.3
Name: astra-logs
Version: 4.2.8
Summary: AI Observability and Evaluation
Project-URL: Documentation, https://docs.arize.com/phoenix/
Project-URL: Issues, https://github.com/Arize-ai/phoenix/issues
Project-URL: Source, https://github.com/Arize-ai/phoenix
Author-email: Alex Andru <alex007d@gmail.com>
License: Elastic-2.0
License-File: IP_NOTICE
License-File: LICENSE
Keywords: Explainability,Monitoring,Observability
Classifier: Programming Language :: Python
Classifier: Programming Language :: Python :: 3.8
Classifier: Programming Language :: Python :: 3.9
Classifier: Programming Language :: Python :: 3.10
Classifier: Programming Language :: Python :: 3.11
Classifier: Programming Language :: Python :: 3.12
Requires-Python: <3.13,>=3.8
Requires-Dist: aioitertools
Requires-Dist: aiosqlite
Requires-Dist: alembic<2,>=1.3.0
Requires-Dist: cachetools
Requires-Dist: grpcio
Requires-Dist: hdbscan>=0.8.33
Requires-Dist: jinja2
Requires-Dist: numpy
Requires-Dist: openinference-instrumentation
Requires-Dist: openinference-instrumentation-langchain>=0.1.12
Requires-Dist: openinference-instrumentation-llama-index>=1.2.0
Requires-Dist: openinference-instrumentation-openai>=0.1.4
Requires-Dist: openinference-semantic-conventions>=0.1.5
Requires-Dist: opentelemetry-exporter-otlp
Requires-Dist: opentelemetry-proto>=1.12.0
Requires-Dist: opentelemetry-sdk
Requires-Dist: opentelemetry-semantic-conventions
Requires-Dist: pandas
Requires-Dist: protobuf<6.0,>=3.20
Requires-Dist: psutil
Requires-Dist: pyarrow
Requires-Dist: requests
Requires-Dist: scikit-learn
Requires-Dist: scipy
Requires-Dist: sqlalchemy[asyncio]<3,>=2.0.4
Requires-Dist: sqlean-py>=3.45.1
Requires-Dist: starlette
Requires-Dist: strawberry-graphql==0.227.2
Requires-Dist: tqdm
Requires-Dist: typing-extensions>=4.5; python_version < '3.12'
Requires-Dist: typing-extensions>=4.6; python_version >= '3.12'
Requires-Dist: umap-learn
Requires-Dist: uvicorn
Requires-Dist: wrapt
Provides-Extra: container
Requires-Dist: opentelemetry-exporter-otlp; extra == 'container'
Requires-Dist: opentelemetry-instrumentation-grpc; extra == 'container'
Requires-Dist: opentelemetry-instrumentation-sqlalchemy; extra == 'container'
Requires-Dist: opentelemetry-instrumentation-starlette; extra == 'container'
Requires-Dist: opentelemetry-proto>=1.12.0; extra == 'container'
Requires-Dist: opentelemetry-sdk; extra == 'container'
Requires-Dist: opentelemetry-semantic-conventions; extra == 'container'
Requires-Dist: prometheus-client; extra == 'container'
Requires-Dist: py-grpc-prometheus; extra == 'container'
Requires-Dist: strawberry-graphql[opentelemetry]==0.227.2; extra == 'container'
Requires-Dist: uvloop; (platform_system != 'Windows') and extra == 'container'
Provides-Extra: dev
Requires-Dist: anthropic; extra == 'dev'
Requires-Dist: arize[autoembeddings,llm-evaluation]; extra == 'dev'
Requires-Dist: asyncpg; extra == 'dev'
Requires-Dist: gcsfs; extra == 'dev'
Requires-Dist: google-cloud-aiplatform>=1.3; extra == 'dev'
Requires-Dist: hatch; extra == 'dev'
Requires-Dist: jupyter; extra == 'dev'
Requires-Dist: langchain>=0.0.334; extra == 'dev'
Requires-Dist: litellm>=1.0.3; extra == 'dev'
Requires-Dist: llama-index>=0.10.3; extra == 'dev'
Requires-Dist: nbqa; extra == 'dev'
Requires-Dist: pandas-stubs<=2.0.2.230605; extra == 'dev'
Requires-Dist: pre-commit; extra == 'dev'
Requires-Dist: prometheus-client; extra == 'dev'
Requires-Dist: psycopg[binary]; extra == 'dev'
Requires-Dist: pytest-asyncio; extra == 'dev'
Requires-Dist: pytest-cov; extra == 'dev'
Requires-Dist: pytest-postgresql; extra == 'dev'
Requires-Dist: pytest==7.4.4; extra == 'dev'
Requires-Dist: ruff==0.3.0; extra == 'dev'
Requires-Dist: strawberry-graphql[debug-server,opentelemetry]==0.227.2; extra == 'dev'
Provides-Extra: evals
Requires-Dist: arize-phoenix-evals>=0.3.0; extra == 'evals'
Provides-Extra: experimental
Requires-Dist: tenacity; extra == 'experimental'
Provides-Extra: llama-index
Requires-Dist: llama-index-callbacks-arize-phoenix>=0.1.2; extra == 'llama-index'
Requires-Dist: llama-index==0.10.3; extra == 'llama-index'
Requires-Dist: openinference-instrumentation-llama-index>=1.2.0; extra == 'llama-index'
Provides-Extra: pg
Requires-Dist: asyncpg; extra == 'pg'
